xieminxuan10.py
xieminxuan10-1.0.3.dist-info/METADATA
xieminxuan10-1.0.3.dist-info/WHEEL
xieminxuan10-1.0.3.dist-info/top_level.txt
xieminxuan10-1.0.3.dist-info/RECORD
