Metadata-Version: 2.1
Name: xieminxuan10
Version: 1.0.3
Summary: 小尝试哦
Home-page: https://gitee.com/siemingsuan
Author: xieminxuan
Author-email: 2091549152@qq.com
License: UNKNOWN
Platform: UNKNOWN
